AUTHORS
COPYING
MANIFEST.in
README
TODO
python-ekg.spec
settings.ini
setup.py
ekg/__init__.py
ekg/commands.py
ekg/core.py
ekg/grapher.py
ekg/model.py
ekg/util.py
ekg.egg-info/PKG-INFO
ekg.egg-info/SOURCES.txt
ekg.egg-info/dependency_links.txt
ekg.egg-info/entry_points.txt
ekg.egg-info/requires.txt
ekg.egg-info/top_level.txt
ekg/migration/__init__.py
ekg/migration/manage.py
ekg/migration/versions/001_Create_Database.py
ekg/migration/versions/__init__.py