Metadata-Version: 1.0
Name: ekg
Version: 0.4.1
Summary: Collect and display statistics about open source projects
Home-page: https://fedorahosted.org/ekg/
Author: Yaakov M. Nemoy
Author-email: ekg@hexago.nl
License: GPLv2+
Platform: UNKNOWN
